Atividade4/registradores_estagios/if_id_register.v
module if_id_register (
  input clock,
  input reset,
  input load,
  input if_flush,
  input [31:0] pc_in,
  input [31:0] instruction_memory_in,
  output [31:0] pc_out,
  output [31:0] instruction
);

  reg [31:0] pc_value;
  reg [31:0] im_value;

  always @(negedge clock) begin
    if (reset || if_flush) begin
      pc_value <= 32'b0;
      im_value <= 32'b0;
    end else if (load) begin
      pc_value <= pc_in;
      im_value <= instruction_memory_in;
    end else begin
      pc_value <= pc_value;
      im_value <= im_value;
    end
  end

  assign pc_out = pc_value;
  assign instruction = im_value;

endmodule

Atividade4/estagios/IF/instruction_memory.v
module instruction_memory (
    input [31:0] addr,        // Endereço de entrada (PC)
    output reg [31:0] instr   // Instrução correspondente ao endereço
);

    // ROM com algumas instruções em formato binário
    always @(*) begin
        case (addr[9:2]) // Usamos 8 bits de endereçamento para 256 instruções
            // Carrega o valor de uma posição de memória no registrador
            // 8'h00: instr = 32'b000000000001_00001_010_00010_0000011; // lw x2, 1(x1)

            // // Armazena o valor de um registrador em uma posição de memória
            // 8'h01: instr = 32'b000000000010_00010_010_00001_0100011; // sw x2, 2(x1)

            // Soma dois registradores
            8'h00: instr = 32'b0000000_00010_00011_000_00100_0110011; // add x4, x3, x2

            // // Subtrai dois registradores
            // 8'h03: instr = 32'b0100000_00010_00011_000_00101_0110011; // sub x5, x3, x2

            // // AND lógico entre dois registradores
            // 8'h04: instr = 32'b0000000_00010_00011_111_00110_0110011; // and x6, x3, x2

            // // OR lógico entre dois registradores
            // 8'h05: instr = 32'b0000000_00010_00011_110_00111_0110011; // or x7, x3, x2

            // // Salta se os valores de dois registradores forem iguais
            // 8'h06: instr = 32'b0000000_00101_00100_000_00001_1100011; // beq x5, x4, +1

            // Finaliza com uma instrução NOP (No Operation)
            8'h01: instr = 32'b0000000_00000_00000_000_00000_0010011; // nop

            default: instr = 32'b0; // Instrução padrão (NOP)
        endcase
    end

endmodule

Atividade4/estagios/IF/program_counter.v
module program_counter(
    input clock,
    input reset,
    input load,
    input [31:0] pc_in,
    output [31:0] pc_out
);

reg [31:0] pc_value;
    always @(posedge clock) begin
        if(reset) begin
            pc_value <= 32'b0;
        end else if(load) begin
            pc_value <= pc_in;
        end else begin
            pc_value <= pc_value;
        end
    end

assign pc_out = pc_value;

endmodule

Atividade4/estagios/EX/mux_2_values.v
module mux_2_values #(
    parameter WIDTH = 32
) (
    input  sel,
    input  [WIDTH-1:0]    D0,
    input  [WIDTH-1:0]    D1,
    output [WIDTH-1:0]    D_out
);

assign D_out = ( sel == 1'b1   ) ? D1 : D0;

endmodule

Atividade4/estagios/IF/IF.v
module fetch (
  input clock,
  input reset,
  input [31:0] pc_branch_value,
  input mux_sel,
  input load_pc,
  input load_if_id_register,
  input if_flush,
  output [31:0] pc_out,
  output [31:0] instrucao
);

  wire [31:0] pc_in_interno, pc_out_interno, instrucao_interno;

  mux_2_values #(
    .WIDTH(32)
  ) mux_instruction_fetch (
    .sel(mux_sel),
    .D0(pc_out_interno + 32'd4),
    .D1(pc_branch_value),
    .D_out(pc_in_interno)
  );

  program_counter pc (
    .clock(clock),
    .reset(reset),
    .load(load_pc),
    .pc_in(pc_in_interno),
    .pc_out(pc_out_interno)
  );

  instruction_memory im (
    .addr(pc_out_interno),
    .instr(instrucao_interno)
  );


  if_id_register if_id_register(
    .clock(clock),
    .reset(reset),
    .load(load_if_id_register),
    .if_flush(if_flush),
    .pc_in(pc_in_interno),
    .instruction_memory_in(instrucao_interno),
    .pc_out(pc_out),
    .instruction(instrucao)
  );





endmodule

Atividade4/estagios/IF/if_tb.v
module fetch_tb;

  // Definindo os sinais
  reg clock;
  reg reset;
  reg [31:0] pc_branch_value;
  reg mux_sel;
  reg load_pc;
  reg load_if_id_register;
  reg if_flush;  // Nova entrada para flush
  wire [31:0] pc_out;
  wire [31:0] instrucao;

  // Instanciando o módulo 'fetch'
  fetch uut (
    .clock(clock),
    .reset(reset),
    .pc_branch_value(pc_branch_value),
    .mux_sel(mux_sel),
    .load_pc(load_pc),
    .load_if_id_register(load_if_id_register),
    .if_flush(if_flush),  // Conexão do novo sinal
    .pc_out(pc_out),
    .instrucao(instrucao)
  );

  // Gerador de clock
  always begin
    #5 clock = ~clock;  // Clock com período de 10 unidades de tempo
  end

  // Inicialização dos sinais e sequência de testes
  initial begin
    // Configuração do dump para o GTKWave
    $dumpfile("fetch_tb.vcd");  // Nome do arquivo de saída
    $dumpvars(0, fetch_tb);     // Dump de todas as variáveis no escopo

    // Inicializando os sinais
    clock = 0;
    reset = 0;
    pc_branch_value = 32'h00000000;  // Valor fictício para PC de branch
    mux_sel = 0;  // Seleciona o incremento de PC normal
    load_pc = 0;
    load_if_id_register = 0;
    if_flush = 0;  // Inicializa sem flush

    // Teste 1: Reset do sistema
    $display("Test 1: Reset");
    reset = 1;  // Ativa o reset
    #10;
    reset = 0;  // Desativa o reset

    // Teste 2: Testando o incremento de PC normal
    $display("Test 2: Incremento de PC");
    load_pc = 1;  // Ativa o carregamento do PC
    load_if_id_register = 1;  // Ativa o carregamento do IF/ID
    #10;

    // Teste 3: Testando o desvio de PC (branch)
    $display("Test 3: Branch no PC");
    mux_sel = 1;  // Seleciona o valor de branch
    pc_branch_value = 32'h00000010;  // Novo valor para o PC (exemplo de branch)
    #10;

    // Teste 4: Ativando o flush
    $display("Test 4: Flush ativado");
    if_flush = 1;  // Ativa o flush
    #10;
    if_flush = 0;  // Desativa o flush

    // Teste 5: Testando novamente sem desvio de PC
    $display("Test 5: Sem Branch");
    mux_sel = 0;  // Seleciona o incremento normal de PC
    #10;

    // Teste 6: Teste com novo carregamento de instrução
    $display("Test 6: Novo Carregamento de Instrução");
    load_pc = 1;  // Carregar o PC
    load_if_id_register = 1;  // Carregar o registro IF/ID
    #10;

    // Finalizando o teste
    $finish;
  end

  // Monitorando as saídas
  initial begin
    $monitor("Time: %0d | PC: %h | Instrução: %h | Flush: %b", $time, pc_out, instrucao, if_flush);
  end

endmodule

Atividade4/fetch_tb.vcd
$date
	Mon Dec  2 15:09:19 2024
$end
$version
	Icarus Verilog
$end
$timescale
	1s
$end
$scope module fetch_tb $end
$var wire 32 ! pc_out [31:0] $end
$var wire 32 " instrucao [31:0] $end
$var reg 1 # clock $end
$var reg 1 $ if_flush $end
$var reg 1 % load_if_id_register $end
$var reg 1 & load_pc $end
$var reg 1 ' mux_sel $end
$var reg 32 ( pc_branch_value [31:0] $end
$var reg 1 ) reset $end
$scope module uut $end
$var wire 1 # clock $end
$var wire 1 $ if_flush $end
$var wire 1 % load_if_id_register $end
$var wire 1 & load_pc $end
$var wire 1 ' mux_sel $end
$var wire 32 * pc_branch_value [31:0] $end
$var wire 1 ) reset $end
$var wire 32 + pc_out_interno [31:0] $end
$var wire 32 , pc_out [31:0] $end
$var wire 32 - pc_in_interno [31:0] $end
$var wire 32 . instrucao_interno [31:0] $end
$var wire 32 / instrucao [31:0] $end
$scope module if_id_register $end
$var wire 1 # clock $end
$var wire 1 $ if_flush $end
$var wire 32 0 instruction [31:0] $end
$var wire 1 % load $end
$var wire 32 1 pc_out [31:0] $end
$var wire 1 ) reset $end
$var wire 32 2 pc_in [31:0] $end
$var wire 32 3 instruction_memory_in [31:0] $end
$var reg 32 4 im_value [31:0] $end
$var reg 32 5 pc_value [31:0] $end
$upscope $end
$scope module im $end
$var wire 32 6 addr [31:0] $end
$var reg 32 7 instr [31:0] $end
$upscope $end
$scope module mux_instruction_fetch $end
$var wire 32 8 D0 [31:0] $end
$var wire 32 9 D1 [31:0] $end
$var wire 1 ' sel $end
$var wire 32 : D_out [31:0] $end
$var parameter 32 ; WIDTH $end
$upscope $end
$scope module pc $end
$var wire 1 # clock $end
$var wire 1 & load $end
$var wire 32 < pc_in [31:0] $end
$var wire 1 ) reset $end
$var wire 32 = pc_out [31:0] $end
$var reg 32 > pc_value [31:0] $end
$upscope $end
$upscope $end
$upscope $end
$enddefinitions $end
$comment Show the parameter values. $end
$dumpall
b100000 ;
$end
#0
$dumpvars
bx >
bx =
bx <
bx :
b0 9
bx 8
bx 7
bx 6
bx 5
bx 4
bx 3
bx 2
bx 1
bx 0
bx /
bx .
bx -
bx ,
bx +
b0 *
1)
b0 (
0'
0&
0%
0$
0#
bx "
bx !
$end
#5
b100 -
b100 2
b100 :
b100 <
b100001010000100000011 .
b100001010000100000011 3
b100001010000100000011 7
b100 8
b0 +
b0 6
b0 =
b0 >
b0 "
b0 /
b0 0
b0 4
b0 !
b0 ,
b0 1
b0 5
1#
#10
0#
1%
1&
0)
#15
b1000 -
b1000 2
b1000 :
b1000 <
b1000010010000010100011 .
b1000010010000010100011 3
b1000010010000010100011 7
b100001010000100000011 "
b100001010000100000011 /
b100001010000100000011 0
b100001010000100000011 4
b100 !
b100 ,
b100 1
b100 5
b1000 8
b100 +
b100 6
b100 =
b100 >
1#
#20
b10000 -
b10000 2
b10000 :
b10000 <
0#
b10000 (
b10000 *
b10000 9
1'
#25
b1000011111001100110011 .
b1000011111001100110011 3
b1000011111001100110011 7
b10100 8
b10000 +
b10000 6
b10000 =
b10000 >
b1000010010000010100011 "
b1000010010000010100011 /
b1000010010000010100011 0
b1000010010000010100011 4
b10000 !
b10000 ,
b10000 1
b10000 5
1#
#30
0#
1$
#35
b0 "
b0 /
b0 0
b0 4
b0 !
b0 ,
b0 1
b0 5
1#
#40
b10100 -
b10100 2
b10100 :
b10100 <
0#
0'
0$
#45
b11000 -
b11000 2
b11000 :
b11000 <
b1000011110001110110011 .
b1000011110001110110011 3
b1000011110001110110011 7
b11000 8
b10100 +
b10100 6
b10100 =
b10100 >
b1000011111001100110011 "
b1000011111001100110011 /
b1000011111001100110011 0
b1000011111001100110011 4
b10100 !
b10100 ,
b10100 1
b10100 5
1#
#50
0#
#55
b11100 -
b11100 2
b11100 :
b11100 <
b10100100000000011100011 .
b10100100000000011100011 3
b10100100000000011100011 7
b1000011110001110110011 "
b1000011110001110110011 /
b1000011110001110110011 0
b1000011110001110110011 4
b11000 !
b11000 ,
b11000 1
b11000 5
b11100 8
b11000 +
b11000 6
b11000 =
b11000 >
1#
