Atividade4/estagios/ID/controle.v
module controle (
  input clock,
  input reset,
  input [6:0] opcode,

  output reg mem_to_reg_out,
  output reg reg_write_out,
  output reg mem_read_out,
  output reg mem_write_out,
  output reg beq_instruction_out,
  output reg aluSrc_out,
  output reg [1:0] aluOp_out
);

  always @(posedge clock or posedge reset) begin
    if (reset) begin
      // Reseta todos os sinais de controle
      mem_to_reg_out        <= 1'b0;
      reg_write_out         <= 1'b0;
      mem_read_out          <= 1'b0;
      mem_write_out         <= 1'b0;
      beq_instruction_out   <= 1'b0;
      aluSrc_out            <= 1'b0;
      aluOp_out             <= 2'b00;
    end else begin
      // Decodificação do opcode
      case (opcode)
        7'b0110011: begin // R-Type (e.g., ADD, SUB)
          mem_to_reg_out        <= 1'b0;
          reg_write_out         <= 1'b1;
          mem_read_out          <= 1'b0;
          mem_write_out         <= 1'b0;
          beq_instruction_out   <= 1'b0;
          aluSrc_out            <= 1'b0;
          aluOp_out             <= 2'b10; // Código para operações R-Type
        end
        7'b0000011: begin // Load (e.g., LW)
          mem_to_reg_out        <= 1'b1;
          reg_write_out         <= 1'b1;
          mem_read_out          <= 1'b1;
          mem_write_out         <= 1'b0;
          beq_instruction_out   <= 1'b0;
          aluSrc_out            <= 1'b1; // Usar imediato
          aluOp_out             <= 2'b00; // Código para LOAD
        end
        7'b0100011: begin // Store (e.g., SW)
          mem_to_reg_out        <= 1'b0; // Não escreve no registrador
          reg_write_out         <= 1'b0;
          mem_read_out          <= 1'b0;
          mem_write_out         <= 1'b1;
          beq_instruction_out   <= 1'b0;
          aluSrc_out            <= 1'b1; // Usar imediato
          aluOp_out             <= 2'b00; // Código para STORE
        end
        7'b1100011: begin // Branch (e.g., BEQ)
          mem_to_reg_out        <= 1'b0;
          reg_write_out         <= 1'b0;
          mem_read_out          <= 1'b0;
          mem_write_out         <= 1'b0;
          beq_instruction_out   <= 1'b1;
          aluSrc_out            <= 1'b0; // Usar valores do registrador
          aluOp_out             <= 2'b01; // Código para BEQ
        end
        default: begin // Caso padrão (instrução não reconhecida)
          mem_to_reg_out        <= 1'b0;
          reg_write_out         <= 1'b0;
          mem_read_out          <= 1'b0;
          mem_write_out         <= 1'b0;
          beq_instruction_out   <= 1'b0;
          aluSrc_out            <= 1'b0;
          aluOp_out             <= 2'b00; // Nenhuma operação
        end
      endcase
    end
  end

endmodule

Atividade4/estagios/ID/controle_tb.v
module controle_tb;

  // Entradas
  reg clock;
  reg reset;
  reg [6:0] opcode;

  // Saídas
  wire mem_to_reg_out;
  wire reg_write_out;
  wire mem_read_out;
  wire mem_write_out;
  wire beq_instruction_out;
  wire aluSrc_out;
  wire [1:0] aluOp_out;

  // Instância do módulo
  controle uut (
    .clock(clock),
    .reset(reset),
    .opcode(opcode),
    .mem_to_reg_out(mem_to_reg_out),
    .reg_write_out(reg_write_out),
    .mem_read_out(mem_read_out),
    .mem_write_out(mem_write_out),
    .beq_instruction_out(beq_instruction_out),
    .aluSrc_out(aluSrc_out),
    .aluOp_out(aluOp_out)
  );

  // Geração de clock
  initial begin
    clock = 0;
    forever #5 clock = ~clock; // Clock com período de 10 unidades de tempo
  end

  // Estímulos de teste
  initial begin
    $dumpfile("controle_tb.vcd");
    $dumpvars(0, controle_tb);

    // Teste 1: Reset
    reset = 1;
    opcode = 7'b0000000; // Valor irrelevante durante o reset
    #10; // Aguarda um ciclo de clock
    reset = 0;

    // Teste 2: R-Type
    opcode = 7'b0110011; // Instruções R-Type
    #10;
    $display("R-Type: mem_to_reg=%b, reg_write=%b, mem_read=%b, mem_write=%b, beq_instruction=%b, aluSrc=%b, aluOp=%b",
             mem_to_reg_out, reg_write_out, mem_read_out, mem_write_out, beq_instruction_out, aluSrc_out, aluOp_out);

    // Teste 3: Load
    opcode = 7'b0000011; // Instruções Load
    #10;
    $display("Load: mem_to_reg=%b, reg_write=%b, mem_read=%b, mem_write=%b, beq_instruction=%b, aluSrc=%b, aluOp=%b",
             mem_to_reg_out, reg_write_out, mem_read_out, mem_write_out, beq_instruction_out, aluSrc_out, aluOp_out);

    // Teste 4: Store
    opcode = 7'b0100011; // Instruções Store
    #10;
    $display("Store: mem_to_reg=%b, reg_write=%b, mem_read=%b, mem_write=%b, beq_instruction=%b, aluSrc=%b, aluOp=%b",
             mem_to_reg_out, reg_write_out, mem_read_out, mem_write_out, beq_instruction_out, aluSrc_out, aluOp_out);

    // Teste 5: Branch
    opcode = 7'b1100011; // Instruções Branch
    #10;
    $display("Branch: mem_to_reg=%b, reg_write=%b, mem_read=%b, mem_write=%b, beq_instruction=%b, aluSrc=%b, aluOp=%b",
             mem_to_reg_out, reg_write_out, mem_read_out, mem_write_out, beq_instruction_out, aluSrc_out, aluOp_out);

    // Teste 6: Opcode desconhecido
    opcode = 7'b1111111; // Instrução inválida
    #10;
    $display("Desconhecido: mem_to_reg=%b, reg_write=%b, mem_read=%b, mem_write=%b, beq_instruction=%b, aluSrc=%b, aluOp=%b",
             mem_to_reg_out, reg_write_out, mem_read_out, mem_write_out, beq_instruction_out, aluSrc_out, aluOp_out);

    $finish; // Finaliza a simulação
  end
endmodule

Atividade4/estagios/ID/controle_tb.vcd
$date
	Sun Dec  1 15:45:16 2024
$end
$version
	Icarus Verilog
$end
$timescale
	1s
$end
$scope module controle_tb $end
$var wire 1 ! reg_write_out $end
$var wire 1 " mem_write_out $end
$var wire 1 # mem_to_reg_out $end
$var wire 1 $ mem_read_out $end
$var wire 1 % beq_instruction_out $end
$var wire 1 & aluSrc_out $end
$var wire 2 ' aluOp_out [1:0] $end
$var reg 1 ( clock $end
$var reg 7 ) opcode [6:0] $end
$var reg 1 * reset $end
$scope module uut $end
$var wire 1 ( clock $end
$var wire 7 + opcode [6:0] $end
$var wire 1 * reset $end
$var reg 2 , aluOp_out [1:0] $end
$var reg 1 & aluSrc_out $end
$var reg 1 % beq_instruction_out $end
$var reg 1 $ mem_read_out $end
$var reg 1 # mem_to_reg_out $end
$var reg 1 " mem_write_out $end
$var reg 1 ! reg_write_out $end
$upscope $end
$upscope $end
$enddefinitions $end
$comment Show the parameter values. $end
$dumpall
$end
#0
$dumpvars
b0 ,
b0 +
1*
b0 )
0(
b0 '
0&
0%
0$
0#
0"
0!
$end
#5
1(
#10
0(
b110011 )
b110011 +
0*
#15
b10 '
b10 ,
1!
1(
#20
0(
b11 )
b11 +
#25
b0 '
b0 ,
1&
1$
1#
1(
#30
0(
b100011 )
b100011 +
#35
1"
0$
0!
0#
1(
#40
0(
b1100011 )
b1100011 +
#45
b1 '
b1 ,
0&
1%
0"
1(
#50
0(
b1111111 )
b1111111 +
#55
b0 '
b0 ,
0%
1(
