Atividade4/estagios/ID/Hazard.v
module hazard_unit(
    input clk,
    input rst,
    input [6:0] inst_opcode,
    input [4:0] src1,
    input [4:0] src2,
    input [4:0] dest_ex_mem,
    input [4:0] dest_mem_wb,
    input branch_ctrl_flag,
    input branch_taken_flag,
    output reg pc_enable,
    output reg if_id_enable,
    output reg stall_pipeline
);

localparam [6:0] TYPE_R = 7'b0110011,
                 TYPE_S = 7'b0100011,
                 TYPE_SB = 7'b1100011,
                 TYPE_I = 7'b0000011;

// Sinal para indicar dependências de dados
wire has_data_hazard;

assign has_data_hazard = (
    ((inst_opcode == TYPE_R) || (inst_opcode == TYPE_S) || (inst_opcode == TYPE_SB) || (inst_opcode == TYPE_I)) &&
    ((src1 != 0) && ((src1 == dest_ex_mem) || (src1 == dest_mem_wb)))
) || (
    ((inst_opcode == TYPE_R) || (inst_opcode == TYPE_S) || (inst_opcode == TYPE_SB)) &&
    ((src2 != 0) && ((src2 == dest_ex_mem) || (src2 == dest_mem_wb)))
);

// Controle do carregamento do PC
always @(*) begin
    if (rst) begin
        pc_enable = 0;
    end else begin
        pc_enable = ~has_data_hazard &&
                    ~((inst_opcode == TYPE_SB) && !branch_taken_flag);
    end
end

// Controle do carregamento do registrador IF/ID
always @(*) begin
    if (rst) begin
        if_id_enable = 0;
    end else begin
        if_id_enable = ~has_data_hazard;
    end
end

// Controle para inserir bolhas no pipeline
always @(*) begin
    if (rst) begin
        stall_pipeline = 0;
    end else begin
        stall_pipeline = has_data_hazard;
    end
end

endmodule

Atividade4/estagios/ID/Hazard_tb.v
`timescale 1ns / 1ps

module hazard_unit_tb;

    reg clk;
    reg rst;
    reg [6:0] inst_opcode;
    reg [4:0] src1;
    reg [4:0] src2;
    reg [4:0] dest_ex_mem;
    reg [4:0] dest_mem_wb;
    reg branch_ctrl_flag;
    reg branch_taken_flag;
    wire pc_enable;
    wire if_id_enable;
    wire stall_pipeline;

    // Instanciação do módulo sob teste
    hazard_unit uut (
        .clk(clk),
        .rst(rst),
        .inst_opcode(inst_opcode),
        .src1(src1),
        .src2(src2),
        .dest_ex_mem(dest_ex_mem),
        .dest_mem_wb(dest_mem_wb),
        .branch_ctrl_flag(branch_ctrl_flag),
        .branch_taken_flag(branch_taken_flag),
        .pc_enable(pc_enable),
        .if_id_enable(if_id_enable),
        .stall_pipeline(stall_pipeline)
    );

    // Geração do clock
    initial begin
        clk = 0;
        forever #5 clk = ~clk; // Clock com período de 10ns
    end

    // Testbench principal
    initial begin
        // Configuração para visualização
        $dumpfile("hazard_unit_tb.vcd");
        $dumpvars(0, hazard_unit_tb);

        // Inicialização
        rst = 1;
        inst_opcode = 7'b0;
        src1 = 5'b0;
        src2 = 5'b0;
        dest_ex_mem = 5'b0;
        dest_mem_wb = 5'b0;
        branch_ctrl_flag = 0;
        branch_taken_flag = 0;

        #10 rst = 0;

        // Teste 1: Sem hazard, PC e IF/ID habilitados
        #10;
        inst_opcode = 7'b0110011; // R-TYPE
        src1 = 5'd1;
        src2 = 5'd2;
        dest_ex_mem = 5'd3;
        dest_mem_wb = 5'd4;

        // Teste 2: Hazard de dados no src1
        #10;
        dest_ex_mem = 5'd1;

        // Teste 3: Hazard de dados no src2
        #10;
        dest_ex_mem = 5'd0;
        dest_mem_wb = 5'd2;

        // Teste 4: Hazard de controle (branch)
        #10;
        inst_opcode = 7'b1100011; // SB-TYPE
        branch_ctrl_flag = 1;
        branch_taken_flag = 0;

        // Teste 5: Hazard de controle resolvido
        #10;
        branch_taken_flag = 1;

        // Teste 6: Reset
        #10;
        rst = 1;

        // Finalização
        #10;
        $finish;
    end

endmodule

Atividade4/estagios/ID/hazard_unit_tb.vcd
$date
	Sun Dec  1 15:09:31 2024
$end
$version
	Icarus Verilog
$end
$timescale
	1ps
$end
$scope module hazard_unit_tb $end
$var wire 1 ! stall_pipeline $end
$var wire 1 " pc_enable $end
$var wire 1 # if_id_enable $end
$var reg 1 $ branch_ctrl_flag $end
$var reg 1 % branch_taken_flag $end
$var reg 1 & clk $end
$var reg 5 ' dest_ex_mem [4:0] $end
$var reg 5 ( dest_mem_wb [4:0] $end
$var reg 7 ) inst_opcode [6:0] $end
$var reg 1 * rst $end
$var reg 5 + src1 [4:0] $end
$var reg 5 , src2 [4:0] $end
$scope module uut $end
$var wire 1 $ branch_ctrl_flag $end
$var wire 1 % branch_taken_flag $end
$var wire 1 & clk $end
$var wire 5 - dest_ex_mem [4:0] $end
$var wire 5 . dest_mem_wb [4:0] $end
$var wire 1 / has_data_hazard $end
$var wire 7 0 inst_opcode [6:0] $end
$var wire 1 * rst $end
$var wire 5 1 src1 [4:0] $end
$var wire 5 2 src2 [4:0] $end
$var parameter 7 3 TYPE_I $end
$var parameter 7 4 TYPE_R $end
$var parameter 7 5 TYPE_S $end
$var parameter 7 6 TYPE_SB $end
$var reg 1 # if_id_enable $end
$var reg 1 " pc_enable $end
$var reg 1 ! stall_pipeline $end
$upscope $end
$upscope $end
$enddefinitions $end
$comment Show the parameter values. $end
$dumpall
b1100011 6
b100011 5
b110011 4
b11 3
$end
#0
$dumpvars
b0 2
b0 1
b0 0
0/
b0 .
b0 -
b0 ,
b0 +
1*
b0 )
b0 (
b0 '
0&
0%
0$
0#
0"
0!
$end
#5000
1&
#10000
1#
1"
0&
0*
#15000
1&
#20000
0&
b100 (
b100 .
b11 '
b11 -
b10 ,
b10 2
b1 +
b1 1
b110011 )
b110011 0
#25000
1&
#30000
1!
0#
0"
1/
0&
b1 '
b1 -
#35000
1&
#40000
0&
b10 (
b10 .
b0 '
b0 -
#45000
1&
#50000
0&
1$
b1100011 )
b1100011 0
#55000
1&
#60000
0&
1%
#65000
1&
#70000
0!
0&
1*
