Atividade4/estagios/EX/ex_mem_register.v
module ex_mem_register (
    input clock,
    input reset,
    // Sinais de controle WB
    input       mem_to_reg_in,
    input       reg_write_in,
    // Sinais de controle MEM
    input       mem_read_in,
    input       mem_write_in,
    input       beq_instruction_in,
    // Sinais de dados
    input [31:0] alu_result_in,
    input [31:0] mux2_result_in,
    input [4:0] reg_rd_in,
    input       flag_beq_in,
    // Saídas sinais de controle WB
    output      mem_to_reg_out,
    output      reg_write_out,
    // Saídas sinais de controle MEM
    output      mem_read_out,
    output      mem_write_out,
    output      beq_instruction_out,
    // Saídas do banco de registradores EX/MEM
    output [31:0] alu_result_out,
    output [31:0] mux2_result_out,
    output [4:0] reg_rd_out,
    output       flag_beq_out
);

reg      mem_to_reg_value;
reg      reg_write_value;
reg      mem_read_value;
reg      beq_instruction_value;
reg [31:0] alu_result_value;
reg [31:0] mux2_result_value;
reg [4:0] reg_rd_value;
reg      flag_beq_value;

    always @(negedge clock) begin
        if(reset) begin
            mem_to_reg_value <= 1'b0;
            reg_write_value <= 1'b0;
            mem_read_value <= 1'b0;
            beq_instruction_value <= 1'b0;
            alu_result_value <= 32'd0;
            mux2_result_value <= 32'd0;
            reg_rd_value <= 5'd0;
            flag_beq_value <= 1'b0;
        end else begin
            mem_to_reg_value <= mem_to_reg_in;
            reg_write_value <= reg_write_in;
            mem_read_value <= mem_read_in;
            beq_instruction_value <= beq_instruction_in;
            alu_result_value <= alu_result_in;
            mux2_result_value <= mux2_result_in;
            reg_rd_value <= reg_rd_in;
            flag_beq_value <= flag_beq_in;
        end
    end

assign mem_to_reg_out = mem_to_reg_value;
assign reg_write_out = reg_write_value;
assign mem_read_out = mem_read_value;
assign beq_instruction_out = beq_instruction_value;
assign alu_result_out = alu_result_value;
assign mux2_result_out = mux2_result_value;
assign reg_rd_out = reg_rd_value;
assign flag_beq_out = flag_beq_value;


endmodule

Atividade4/estagios/EX/forwading_unit.v
module forwarding_unit(
    input [4:0] id_ex_reg_rs1,
    input [4:0] id_ex_reg_rs2,
    input       ex_mem_reg_write,
    input [4:0] ex_mem_reg_rd,
    input       mem_wb_reg_write,
    input [4:0] mem_wb_reg_rd,
    output [1:0] forwardA,
    output [1:0] forwardB
);

assign forwardA = (ex_mem_reg_write && (ex_mem_reg_rd != 0) && (ex_mem_reg_rd == id_ex_reg_rs1)) ? 2'b10 : 
                  (mem_wb_reg_write && (mem_wb_reg_rd != 0) && (mem_wb_reg_rd == id_ex_reg_rs1)) ? 2'b01 :
                  2'b00;

assign forwardB = (ex_mem_reg_write && (ex_mem_reg_rd != 0) && (ex_mem_reg_rd == id_ex_reg_rs2)) ? 2'b10 : 
                  (mem_wb_reg_write && (mem_wb_reg_rd != 0) && (mem_wb_reg_rd == id_ex_reg_rs2)) ? 2'b01 :
                  2'b00;                  

endmodule

Atividade4/estagios/EX/alu_control.v
module alu_control(
    input  [6:0] funct7,
    input  [2:0] funct3,
    input  [1:0] aluOp,
    output reg [3:0] op
);

    // Lista de operações
    // op = 0010 : add
    // op = 0110 : sub
    // op = 0000 : and
    // op = 0001 : or

    always @(*) begin
        case (aluOp)
            2'b00: begin
                op <= 4'b0010; //add (ld e sd)
            end 
            2'b01: begin
                op <= 4'b0110; // sub (beq)
            end
            2'b10:begin
                case (funct7)
                    7'b0100000: begin
                        op <= 4'b0110; // sub
                    end
                    7'b0000000: begin
                        case (funct3)
                            3'b000: begin
                                op <= 4'b0010; // add
                            end 
                            3'b110: begin
                                op <= 4'b0001; // or
                            end
                            3'b111: begin
                                op <= 4'b0000; // and
                            end
                            default: begin
                                op <= 4'b0010;
                            end
                        endcase
                    end 
                    default: begin
                        op <= 4'b0010;
                    end
                endcase
            end
            default: begin
                op <= 4'b0010;
            end
        endcase
    end

endmodule

Atividade4/estagios/EX/alu.v
module alu (
	input   [31:0] a, b,
	input   [3:0 ] op, 
	output  [31:0] res, 
	output         flag
);  

    // Lista de operações
    // op = 0010 : add
    // op = 0110 : sub
    // op = 0000 : and
    // op = 0001 : or

	assign res = (op == 4'b0010) ? a + b :          // add
                 (op == 4'b0110) ? a + ((~b) + 1) : // sub
				 (op == 4'b0000) ? a & b :          // and
                 (op == 4'b0001) ? a | b : 32'd0;   // or

    assign flag = (a == b) ? 1 : 0; // beq

endmodule

Atividade4/estagios/EX/mux_2_values.v
module mux_2_values #(
    parameter WIDTH = 32
) (
    input  sel,
    input  [WIDTH-1:0]    D0,
    input  [WIDTH-1:0]    D1,
    output [WIDTH-1:0]    D_out
);

assign D_out = ( sel == 1'b1   ) ? D1 : D0;

endmodule

Atividade4/estagios/EX/mux_3_values.v
module mux_3_values #(
    parameter WIDTH = 32
) (
    input  [1:0]          sel,
    input  [WIDTH-1:0]    D0,
    input  [WIDTH-1:0]    D1,
    input  [WIDTH-1:0]    D2,
    output [WIDTH-1:0]    D_out
);

assign D_out = ( sel == 2'b00   ) ? D0 : 
               ( sel == 2'b01   ) ? D1 :        
               ( sel == 2'b10   ) ? D2 : D0;

endmodule

Atividade4/estagios/EX/EX.v
module EX (
    input       clock,
    input       reset,
    // Sinais de entrada de dados
    input [31:0] reg_a_in,
    input [31:0] reg_b_in,
    // Sinais de controle WB
    input       mem_to_reg_in,
    input       reg_write_in,
    // Sinais de controle MEM
    input       mem_read_in,
    input       mem_write_in,
    input       beq_instruction_in,
    // Sinais de controle EX
    input       aluSrc_in,
    input [1:0] aluOp_in,
    // Demais entradas de registrados e imediato
    input [6:0] funct7_in,
    input [2:0] funct3_in,
    input [4:0] reg_rs1_in,
    input [4:0] reg_rs2_in,
    input [4:0] reg_rd_in,
    input [31:0] immediate_in,
    // Sinais de entrada para o forwarding
    input [4:0] ex_mem_reg_rd,
    input       ex_mem_reg_write,
    input [4:0] mem_wb_reg_rd,
    input       mem_wb_reg_write,
    input [31:0] alu_ex_mem,
    input [31:0] alu_data_mem_wb,
    // Saídas sinais de controle WB
    output      mem_to_reg_out,
    output      reg_write_out,
    // Saídas sinais de controle MEM
    output      mem_read_out,
    output      mem_write_out,
    output      beq_instruction_out,
    // Saídas do banco de registradores EX/MEM
    output [31:0] alu_result_out,
    output [31:0] mux2_result_out,
    output [4:0] reg_rd_out,
    output flag_beq_out
);


wire [3:0 ] op_alu;
wire [31:0] mux1_out;
wire [31:0] mux2_out;
wire [31:0] mux3_out;
wire [31:0] alu_result;
wire        flag_beq;
wire [1:0]  forwardA;
wire [1:0]  forwardB;

mux_3_values #(
   .WIDTH(32)
) mux1 (
    .sel(forwardA),
    .D0(reg_a_in),
    .D1(alu_ex_mem),
    .D2(alu_data_mem_wb),
    .D_out(mux1_out)
);

mux_3_values #(
   .WIDTH(32)
) mux2 (
    .sel(forwardB),
    .D0(reg_b_in),
    .D1(alu_ex_mem),
    .D2(alu_data_mem_wb),
    .D_out(mux2_out)
);

mux_2_values #(
    .WIDTH(32)
  ) mux3 (
    .sel(aluSrc_in),
    .D0(mux2_out),
    .D1(immediate_in),
    .D_out(mux3_out)
  );

alu alu_ex(
	.a(mux1_out), 
    .b(mux3_out),
	.op(op_alu), 
	.res(alu_result), 
	.flag(flag_beq)
);  

alu_control alu_control_ex(
    .aluOp(aluOp_in),
    .funct7(funct7_in),
    .funct3(funct3_in),
    .op(op_alu)
);

forwarding_unit forward(
    .id_ex_reg_rs1(reg_rs1_in),
    .id_ex_reg_rs2(reg_rs2_in),
    .ex_mem_reg_write(ex_mem_reg_write),
    .ex_mem_reg_rd(ex_mem_reg_rd),
    .mem_wb_reg_write(mem_wb_reg_write),
    .mem_wb_reg_rd(mem_wb_reg_rd),
    .forwardA(forwardA),
    .forwardB(forwardB)
);

ex_mem_register ex_mem_reg (
    .clock(clock),
    .reset(reset),
    // Sinais de controle WB
    .mem_to_reg_in(mem_to_reg_in),
    .reg_write_in(reg_write_in),
    // Sinais de controle MEM
    .mem_read_in(mem_read_in),
    .mem_write_in(mem_write_in),
    .beq_instruction_in(beq_instruction_in),
    // Sinais de dados
    .alu_result_in(alu_result),
    .mux2_result_in(mux2_out),
    .reg_rd_in(reg_rd_in),
    .flag_beq_in(flag_beq),
    // Saídas sinais de controle WB
    .mem_to_reg_out(mem_to_reg_out),
    .reg_write_out(reg_write_out),
    // Saídas sinais de controle MEM
    .mem_read_out(mem_read_out),
    .mem_write_out(mem_write_out),
    .beq_instruction_out(beq_instruction_out),
    // Saídas do banco de registradores EX/MEM
    .alu_result_out(alu_result_out),
    .mux2_result_out(mux2_result_out),
    .reg_rd_out(reg_rd_out),
    .flag_beq_out(flag_beq_out)
);

endmodule

Atividade4/estagios/EX/EX_tb.v
`timescale 1ns/1ps

module EX_tb;

    // Entradas
    reg clock, reset;
    reg [31:0] reg_a_in, reg_b_in, immediate_in;
    reg mem_to_reg_in, reg_write_in, mem_read_in, mem_write_in, beq_instruction_in;
    reg aluSrc_in;
    reg [1:0] aluOp_in;
    reg [6:0] funct7_in;
    reg [2:0] funct3_in;
    reg [4:0] reg_rs1_in, reg_rs2_in, reg_rd_in, ex_mem_reg_rd, mem_wb_reg_rd;
    reg ex_mem_reg_write, mem_wb_reg_write;
    reg [31:0] alu_ex_mem, alu_data_mem_wb;

    // Saídas
    wire mem_to_reg_out, reg_write_out, mem_read_out, mem_write_out, beq_instruction_out;
    wire [31:0] alu_result_out, mux2_result_out;
    wire [4:0] reg_rd_out;
    wire flag_beq_out;

    // Instância do módulo EX
    EX uut (
        .clock(clock),
        .reset(reset),
        .reg_a_in(reg_a_in),
        .reg_b_in(reg_b_in),
        .immediate_in(immediate_in),
        .mem_to_reg_in(mem_to_reg_in),
        .reg_write_in(reg_write_in),
        .mem_read_in(mem_read_in),
        .mem_write_in(mem_write_in),
        .beq_instruction_in(beq_instruction_in),
        .aluSrc_in(aluSrc_in),
        .aluOp_in(aluOp_in),
        .funct7_in(funct7_in),
        .funct3_in(funct3_in),
        .reg_rs1_in(reg_rs1_in),
        .reg_rs2_in(reg_rs2_in),
        .reg_rd_in(reg_rd_in),
        .ex_mem_reg_rd(ex_mem_reg_rd),
        .ex_mem_reg_write(ex_mem_reg_write),
        .mem_wb_reg_rd(mem_wb_reg_rd),
        .mem_wb_reg_write(mem_wb_reg_write),
        .alu_ex_mem(alu_ex_mem),
        .alu_data_mem_wb(alu_data_mem_wb),
        .mem_to_reg_out(mem_to_reg_out),
        .reg_write_out(reg_write_out),
        .mem_read_out(mem_read_out),
        .mem_write_out(mem_write_out),
        .beq_instruction_out(beq_instruction_out),
        .alu_result_out(alu_result_out),
        .mux2_result_out(mux2_result_out),
        .reg_rd_out(reg_rd_out),
        .flag_beq_out(flag_beq_out)
    );

    // Clock de 10ns
    always #5 clock = ~clock;

    initial begin
        $dumpfile("a.vcd");
        $dumpvars(0, EX_tb);
        // Inicialização
        clock = 0;
        reset = 1;
        reg_a_in = 0; reg_b_in = 0; immediate_in = 0;
        mem_to_reg_in = 0; reg_write_in = 0; mem_read_in = 0; mem_write_in = 0; beq_instruction_in = 0;
        aluSrc_in = 0; aluOp_in = 0;
        funct7_in = 0; funct3_in = 0;
        reg_rs1_in = 0; reg_rs2_in = 0; reg_rd_in = 0;
        ex_mem_reg_rd = 0; ex_mem_reg_write = 0;
        mem_wb_reg_rd = 0; mem_wb_reg_write = 0;
        alu_ex_mem = 0; alu_data_mem_wb = 0;

        // Aguardar alguns ciclos para reset
        #10 reset = 0;

        // Teste 1: Operação ADD (sem imediato, sem forwarding)
        aluOp_in = 2'b10;         // Código de operação para ALU
        funct7_in = 7'b0000000;   // Função para ADD
        funct3_in = 3'b000;
        reg_a_in = 32'h00000005;  // Operando A
        reg_b_in = 32'h00000003;  // Operando B
        aluSrc_in = 0;            // Selecionar registrador como fonte

        #10;
        // Verificar resultado
        if (uut.alu_result != 32'h00000008)
            $display("Erro no Teste 1: alu_result = %h, esperado = 8", uut.alu_result);
        else
            $display("Teste 1: PASSOU - alu_result = %h", uut.alu_result);


        #10
        // Teste 2: Operação SUB
        aluOp_in = 2'b10;
        funct7_in = 7'b0100000;
        funct3_in = 3'b000; 

        #10;
        // Verificar resultado
        if (uut.alu_result != 32'h00000002)
            $display("Erro no Teste 2: alu_result = %h, esperado = 2", uut.alu_result);
        else
            $display("Teste 2: PASSOU - alu_result = %h", uut.alu_result);

        #10
        // Teste 3: Operação OR
        aluOp_in = 2'b10;
        funct7_in = 7'b0000000;
        funct3_in = 3'b110;
        reg_a_in = 32'b10000001000000000000000010000001;  // Operando A
        reg_b_in = 32'b00000000100000011000000100000000;  // Operando B 

        #10;
        // Verificar resultado
        if (uut.alu_result != 32'b10000001100000011000000110000001)
            $display("Erro no Teste 3: alu_result = %b", uut.alu_result);
        else
            $display("Teste 3: PASSOU - alu_result = %b", uut.alu_result);

         #10
        // Teste 4: Operação AND
        aluOp_in = 2'b10;
        funct7_in = 7'b0000000;
        funct3_in = 3'b111;
        reg_a_in = 32'b10000001000000000000000010000001;  // Operando A
        reg_b_in = 32'b10000001100000011000000100000001;  // Operando B 

        #10;
        // Verificar resultado
        if (uut.alu_result != 32'b10000001000000000000000000000001)
            $display("Erro no Teste 4: alu_result = %b", uut.alu_result);
        else
            $display("Teste 4: PASSOU - alu_result = %b", uut.alu_result);

         #10
        // Teste 5: Operação ADD (ld ou sd)
        aluOp_in = 2'b00;
        reg_a_in = 32'h00000008;  // Operando A
        reg_b_in = 32'h00000001;  // Operando B 

        #10;
        // Verificar resultado
        if (uut.alu_result != 32'h00000009)
            $display("Erro no Teste 5: alu_result = %h", uut.alu_result);
        else
            $display("Teste 5: PASSOU - alu_result = %h", uut.alu_result);

        #10
        // Teste 6: Operação SUB (beq)
        aluOp_in = 2'b01;
        reg_a_in = 32'h10000005;  // Operando A
        reg_b_in = 32'h10000005;  // Operando B 

        #10;
        // Verificar resultado
        if (uut.flag_beq != 1'b1)
            $display("Erro no Teste 6: flag_beq = %b", uut.flag_beq);
        else
            $display("Teste 6: PASSOU - flag_beq = %b - alu_result = %h", uut.flag_beq, uut.alu_result);
        
        #10
        // Teste 7: Operação ADD com imediato
        aluOp_in = 2'b10;         // Código de operação para ALU
        funct7_in = 7'b0000000;   // Função para ADD
        funct3_in = 3'b000;
        reg_a_in = 32'h00000005;  // Operando A
        reg_b_in = 32'h00000003;  // Operando B
        immediate_in = 32'h00000002; // Valor imediato
        aluSrc_in = 1;               // Selecionar imediato como fonte
        #10;

        // Verificar resultado
        if (uut.alu_result != 32'h00000007)
            $display("Erro no Teste 7: alu_result = %h, esperado = 7", uut.alu_result);
        else
            $display("Teste 7: PASSOU - alu_result = %h", uut.alu_result);

        // Teste 8: Forwarding (registradores diferentes)
        ex_mem_reg_rd = 5'b00001;   // Registrador de destino no estágio EX/MEM
        ex_mem_reg_write = 1;      // Habilitar escrita
        mem_wb_reg_rd = 5'b00010;  // Registrador de destino no estágio MEM/WB
        mem_wb_reg_write = 1;      // Habilitar escrita
        alu_ex_mem = 32'h00000009; // Valor calculado no estágio EX/MEM
        alu_data_mem_wb = 32'h00000001; // Valor calculado no estágio MEM/WB
        reg_rs1_in = 5'b00001;     // Registrador fonte 1 depende do estágio EX/MEM
        reg_rs2_in = 5'b00010;     // Registrador fonte 2 depende do estágio MEM/WB
        aluSrc_in = 0;
        #10;

        $display("Teste 8");
        $display("Forwarding - ForwardA = %b, ForwardB = %b", uut.forwardA, uut.forwardB);
        $display("ULA: a = %h - b = %h, - alu_result = %h", uut.alu_ex.b, uut.alu_ex.a, uut.alu_result);
        $display("REG_A = %h -- REG_B = %h", uut.reg_a_in, uut.reg_b_in);

        // Finalizar simulação
        #10 $finish;
    end

endmodule

Atividade4/estagios/EX/a.vcd
$date
	Sun Dec 01 17:19:25 2024
$end
$version
	Icarus Verilog
$end
$timescale
	1ps
$end
$scope module EX_tb $end
$var wire 1 ! mem_write_out $end
$var wire 1 " reg_write_out $end
$var wire 5 # reg_rd_out [4:0] $end
$var wire 32 $ mux2_result_out [31:0] $end
$var wire 1 % mem_to_reg_out $end
$var wire 1 & mem_read_out $end
$var wire 1 ' flag_beq_out $end
$var wire 1 ( beq_instruction_out $end
$var wire 32 ) alu_result_out [31:0] $end
$var reg 2 * aluOp_in [1:0] $end
$var reg 1 + aluSrc_in $end
$var reg 32 , alu_data_mem_wb [31:0] $end
$var reg 32 - alu_ex_mem [31:0] $end
$var reg 1 . beq_instruction_in $end
$var reg 1 / clock $end
$var reg 5 0 ex_mem_reg_rd [4:0] $end
$var reg 1 1 ex_mem_reg_write $end
$var reg 3 2 funct3_in [2:0] $end
$var reg 7 3 funct7_in [6:0] $end
$var reg 32 4 immediate_in [31:0] $end
$var reg 1 5 mem_read_in $end
$var reg 1 6 mem_to_reg_in $end
$var reg 5 7 mem_wb_reg_rd [4:0] $end
$var reg 1 8 mem_wb_reg_write $end
$var reg 1 9 mem_write_in $end
$var reg 32 : reg_a_in [31:0] $end
$var reg 32 ; reg_b_in [31:0] $end
$var reg 5 < reg_rd_in [4:0] $end
$var reg 5 = reg_rs1_in [4:0] $end
$var reg 5 > reg_rs2_in [4:0] $end
$var reg 1 ? reg_write_in $end
$var reg 1 @ reset $end
$scope module uut $end
$var wire 2 A aluOp_in [1:0] $end
$var wire 1 + aluSrc_in $end
$var wire 32 B alu_data_mem_wb [31:0] $end
$var wire 32 C alu_ex_mem [31:0] $end
$var wire 1 . beq_instruction_in $end
$var wire 1 / clock $end
$var wire 5 D ex_mem_reg_rd [4:0] $end
$var wire 1 1 ex_mem_reg_write $end
$var wire 3 E funct3_in [2:0] $end
$var wire 7 F funct7_in [6:0] $end
$var wire 32 G immediate_in [31:0] $end
$var wire 1 5 mem_read_in $end
$var wire 1 6 mem_to_reg_in $end
$var wire 5 H mem_wb_reg_rd [4:0] $end
$var wire 1 8 mem_wb_reg_write $end
$var wire 1 9 mem_write_in $end
$var wire 1 ! mem_write_out $end
$var wire 32 I reg_a_in [31:0] $end
$var wire 32 J reg_b_in [31:0] $end
$var wire 5 K reg_rd_in [4:0] $end
$var wire 5 L reg_rs1_in [4:0] $end
$var wire 5 M reg_rs2_in [4:0] $end
$var wire 1 ? reg_write_in $end
$var wire 1 @ reset $end
$var wire 1 " reg_write_out $end
$var wire 5 N reg_rd_out [4:0] $end
$var wire 4 O op_alu [3:0] $end
$var wire 32 P mux3_out [31:0] $end
$var wire 32 Q mux2_result_out [31:0] $end
$var wire 32 R mux2_out [31:0] $end
$var wire 32 S mux1_out [31:0] $end
$var wire 1 % mem_to_reg_out $end
$var wire 1 & mem_read_out $end
$var wire 2 T forwardB [1:0] $end
$var wire 2 U forwardA [1:0] $end
$var wire 1 ' flag_beq_out $end
$var wire 1 V flag_beq $end
$var wire 1 ( beq_instruction_out $end
$var wire 32 W alu_result_out [31:0] $end
$var wire 32 X alu_result [31:0] $end
$scope module alu_control_ex $end
$var wire 2 Y aluOp [1:0] $end
$var wire 3 Z funct3 [2:0] $end
$var wire 7 [ funct7 [6:0] $end
$var reg 4 \ op [3:0] $end
$upscope $end
$scope module alu_ex $end
$var wire 4 ] op [3:0] $end
$var wire 32 ^ res [31:0] $end
$var wire 1 V flag $end
$var wire 32 _ b [31:0] $end
$var wire 32 ` a [31:0] $end
$upscope $end
$scope module ex_mem_reg $end
$var wire 32 a alu_result_in [31:0] $end
$var wire 32 b alu_result_out [31:0] $end
$var wire 1 . beq_instruction_in $end
$var wire 1 ( beq_instruction_out $end
$var wire 1 / clock $end
$var wire 1 V flag_beq_in $end
$var wire 1 ' flag_beq_out $end
$var wire 1 5 mem_read_in $end
$var wire 1 & mem_read_out $end
$var wire 1 6 mem_to_reg_in $end
$var wire 1 % mem_to_reg_out $end
$var wire 1 9 mem_write_in $end
$var wire 1 ! mem_write_out $end
$var wire 32 c mux2_result_out [31:0] $end
$var wire 5 d reg_rd_in [4:0] $end
$var wire 5 e reg_rd_out [4:0] $end
$var wire 1 ? reg_write_in $end
$var wire 1 " reg_write_out $end
$var wire 1 @ reset $end
$var wire 32 f mux2_result_in [31:0] $end
$var reg 32 g alu_result_value [31:0] $end
$var reg 1 h beq_instruction_value $end
$var reg 1 i flag_beq_value $end
$var reg 1 j mem_read_value $end
$var reg 1 k mem_to_reg_value $end
$var reg 32 l mux2_result_value [31:0] $end
$var reg 5 m reg_rd_value [4:0] $end
$var reg 1 n reg_write_value $end
$upscope $end
$scope module forward $end
$var wire 5 o ex_mem_reg_rd [4:0] $end
$var wire 1 1 ex_mem_reg_write $end
$var wire 5 p id_ex_reg_rs1 [4:0] $end
$var wire 5 q id_ex_reg_rs2 [4:0] $end
$var wire 5 r mem_wb_reg_rd [4:0] $end
$var wire 1 8 mem_wb_reg_write $end
$var wire 2 s forwardB [1:0] $end
$var wire 2 t forwardA [1:0] $end
$upscope $end
$scope module mux1 $end
$var wire 32 u D0 [31:0] $end
$var wire 32 v D1 [31:0] $end
$var wire 32 w D2 [31:0] $end
$var wire 2 x sel [1:0] $end
$var wire 32 y D_out [31:0] $end
$upscope $end
$scope module mux2 $end
$var wire 32 z D0 [31:0] $end
$var wire 32 { D1 [31:0] $end
$var wire 32 | D2 [31:0] $end
$var wire 2 } sel [1:0] $end
$var wire 32 ~ D_out [31:0] $end
$upscope $end
$scope module mux3 $end
$var wire 32 !" D0 [31:0] $end
$var wire 32 "" D1 [31:0] $end
$var wire 1 + sel $end
$var wire 32 #" D_out [31:0] $end
$upscope $end
$upscope $end
$upscope $end
$enddefinitions $end
#0
$dumpvars
b0 #"
b0 ""
b0 !"
b0 ~
b0 }
b0 |
b0 {
b0 z
b0 y
b0 x
b0 w
b0 v
b0 u
b0 t
b0 s
b0 r
b0 q
b0 p
b0 o
0n
b0 m
b0 l
0k
0j
0i
0h
b0 g
b0 f
b0 e
b0 d
b0 c
b0 b
b0 a
b0 `
b0 _
b0 ^
b10 ]
b10 \
b0 [
b0 Z
b0 Y
b0 X
b0 W
1V
b0 U
b0 T
b0 S
b0 R
b0 Q
b0 P
b10 O
b0 N
b0 M
b0 L
b0 K
b0 J
b0 I
b0 H
b0 G
b0 F
b0 E
b0 D
b0 C
b0 B
b0 A
1@
0?
b0 >
b0 =
b0 <
b0 ;
b0 :
09
08
b0 7
06
05
b0 4
b0 3
b0 2
01
b0 0
0/
0.
b0 -
b0 ,
0+
b0 *
b0 )
0(
0'
0&
0%
b0 $
b0 #
0"
z!
$end
#5000
1/
#10000
1'
1i
b11 $
b11 Q
b11 c
b11 l
0V
b11 P
b11 _
b11 #"
b1000 X
b1000 ^
b1000 a
b11 R
b11 f
b11 ~
b11 !"
b101 S
b101 `
b101 y
0/
b11 ;
b11 J
b11 z
b101 :
b101 I
b101 u
b10 *
b10 A
b10 Y
0@
#15000
1/
#20000
0'
0i
b1000 )
b1000 W
b1000 b
b1000 g
0/
#25000
1/
#30000
b10 X
b10 ^
b10 a
b110 O
b110 \
b110 ]
0/
b100000 3
b100000 F
b100000 [
#35000
1/
#40000
b10 )
b10 W
b10 b
b10 g
0/
#45000
1/
#50000
0V
b100000011000000100000000 $
b100000011000000100000000 Q
b100000011000000100000000 c
b100000011000000100000000 l
b1 O
b1 \
b1 ]
b10000001100000011000000110000001 X
b10000001100000011000000110000001 ^
b10000001100000011000000110000001 a
b100000011000000100000000 P
b100000011000000100000000 _
b100000011000000100000000 #"
b100000011000000100000000 R
b100000011000000100000000 f
b100000011000000100000000 ~
b100000011000000100000000 !"
b10000001000000000000000010000001 S
b10000001000000000000000010000001 `
b10000001000000000000000010000001 y
0/
b100000011000000100000000 ;
b100000011000000100000000 J
b100000011000000100000000 z
b10000001000000000000000010000001 :
b10000001000000000000000010000001 I
b10000001000000000000000010000001 u
b110 2
b110 E
b110 Z
b0 3
b0 F
b0 [
#55000
1/
#60000
b10000001100000011000000110000001 )
b10000001100000011000000110000001 W
b10000001100000011000000110000001 b
b10000001100000011000000110000001 g
0/
#65000
1/
#70000
b10000001000000000000000000000001 X
b10000001000000000000000000000001 ^
b10000001000000000000000000000001 a
b10000001100000011000000100000001 $
b10000001100000011000000100000001 Q
b10000001100000011000000100000001 c
b10000001100000011000000100000001 l
b0 O
b0 \
b0 ]
b10000001100000011000000100000001 P
b10000001100000011000000100000001 _
b10000001100000011000000100000001 #"
b10000001100000011000000100000001 R
b10000001100000011000000100000001 f
b10000001100000011000000100000001 ~
b10000001100000011000000100000001 !"
0/
b10000001100000011000000100000001 ;
b10000001100000011000000100000001 J
b10000001100000011000000100000001 z
b111 2
b111 E
b111 Z
#75000
1/
#80000
b10000001000000000000000000000001 )
b10000001000000000000000000000001 W
b10000001000000000000000000000001 b
b10000001000000000000000000000001 g
0/
#85000
1/
#90000
b1 $
b1 Q
b1 c
b1 l
b10 O
b10 \
b10 ]
0V
b1001 X
b1001 ^
b1001 a
b1 P
b1 _
b1 #"
b1 R
b1 f
b1 ~
b1 !"
b1000 S
b1000 `
b1000 y
0/
b1 ;
b1 J
b1 z
b1000 :
b1000 I
b1000 u
b0 *
b0 A
b0 Y
#95000
1/
#100000
b1001 )
b1001 W
b1001 b
b1001 g
0/
#105000
1/
#110000
1V
b10000000000000000000000000101 $
b10000000000000000000000000101 Q
b10000000000000000000000000101 c
b10000000000000000000000000101 l
b110 O
b110 \
b110 ]
b10000000000000000000000000101 P
b10000000000000000000000000101 _
b10000000000000000000000000101 #"
b0 X
b0 ^
b0 a
b10000000000000000000000000101 R
b10000000000000000000000000101 f
b10000000000000000000000000101 ~
b10000000000000000000000000101 !"
b10000000000000000000000000101 S
b10000000000000000000000000101 `
b10000000000000000000000000101 y
0/
b10000000000000000000000000101 ;
b10000000000000000000000000101 J
b10000000000000000000000000101 z
b10000000000000000000000000101 :
b10000000000000000000000000101 I
b10000000000000000000000000101 u
b1 *
b1 A
b1 Y
#115000
1/
#120000
1'
1i
b0 )
b0 W
b0 b
b0 g
0/
#125000
1/
#130000
b11 $
b11 Q
b11 c
b11 l
b10 O
b10 \
b10 ]
0V
b111 X
b111 ^
b111 a
b10 P
b10 _
b10 #"
b11 R
b11 f
b11 ~
b11 !"
b101 S
b101 `
b101 y
0/
1+
b10 4
b10 G
b10 ""
b11 ;
b11 J
b11 z
b101 :
b101 I
b101 u
b0 2
b0 E
b0 Z
b10 *
b10 A
b10 Y
#135000
1/
#140000
0'
0i
b111 )
b111 W
b111 b
b111 g
b1 S
b1 `
b1 y
b1001 R
b1001 f
b1001 ~
b1001 !"
b1 T
b1 s
b1 }
b1010 X
b1010 ^
b1010 a
b10 U
b10 t
b10 x
b1001 P
b1001 _
b1001 #"
0/
0+
b10 >
b10 M
b10 q
b1 =
b1 L
b1 p
b1 ,
b1 B
b1 w
b1 |
b1001 -
b1001 C
b1001 v
b1001 {
18
b10 7
b10 H
b10 r
11
b1 0
b1 D
b1 o
#145000
1/
#150000
b1001 $
b1001 Q
b1001 c
b1001 l
b1010 )
b1010 W
b1010 b
b1010 g
0/
